{
  "locales": {
    "en": {
      "title": "<span class='text-primary'>Skill</span> Set",
      "description": "Exploring the diverse range of skills I've acquired and developed:"
    },
    "de": {
      "title": "<span class='text-primary'>Fertigkeitssatz</span>",
      "description": "Erkundung der vielfältigen Fähigkeiten, die ich erworben und entwickelt habe:"
    },
    "fr": {
      "title": "Ensemble de <span class='text-primary'>Compétences</span>",
      "description": "Exploration de la gamme variée de compétences que j'ai acquises et développées:"
    }
  },

  "subcategories": [
    {
      "id": "abilities",
      "type": "grid",
      "progress": null,
      "faIcon": "fa-solid fa-square",
      "locales": {
        "en": { "title": null }
      }
    },

    {
      "id": "programming",
      "type": "grid",
      "progress": "number",
      "faIcon": "fa fa-code",
      "locales": {
        "en": { "title": "Programming" },
        "de": { "title": "Programmierung" },
        "fr": { "title": "Programmation" }
      }
    },

    {
      "id": "languages",
      "type": "list",
      "progress": {
        "0": "beginner",
        "20": "rookie",
        "40": "intermediate",
        "60": "advanced",
        "80": "fluent",
        "100": "native"
      },
      "faIcon": "fa fa-language",
      "locales": {
        "en": { "title": "Languages" },
        "de": { "title": "Sprachen" },
        "fr": { "title": "Langues" }
      }
    },

    {
      "id": "extra",
      "type": "grid",
      "progress": null,
      "faIcon": "fa fa-marker",
      "locales": {
        "en": { "title": "Bonus" },
        "de": { "title": "Bonus" },
        "fr": { "title": "Plus" }
      }
    }
  ],

  "items": {
    "abilities": [
      {
        "imageIconUrl": null,
        "faIcon": "fas fa-network-wired",
        "value": null,
        "locales": {
          "en": {
            "title": "APIs",
            "description": "Strong knowledge of API structuring, including documentation, architecture, security, and API design best practices."
          },
          "de": {
            "title": "APIs",
            "description": "Fundiertes Wissen über API-Strukturierung, einschließlich Dokumentation, Architektur, Sicherheit und Best Practices für API-Design."
          },
          "fr": {
            "title": "APIs",
            "description": "Solide connaissance de la structuration des API, y compris la documentation, l'architecture, la sécurité et les meilleures pratiques de conception d'API."
          }
        }
      },

      {
        "imageIconUrl": null,
        "faIcon": "fas fa-file-circle-exclamation",
        "value": null,
        "locales": {
          "en": {
            "title": "Tech Requirements",
            "description": "Translating business needs into precise technical specifications for development."
          },
          "de": {
            "title": "Technische Anforderungen",
            "description": "Übersetzung von Geschäftsanforderungen in präzise technische Spezifikationen für die Entwicklung."
          },
          "fr": {
            "title": "Exigences techniques",
            "description": "Traduction des besoins métier en spécifications techniques précises pour le développement."
          }
        }
      },

      {
        "imageIconUrl": null,
        "faIcon": "fas fa-microscope",
        "value": null,
        "locales": {
          "en": {
            "title": "Testing & Quality Assurance",
            "description": "Ensuring the reliability and performance of software through rigorous testing and adherence to quality standards."
          },
          "de": {
            "title": "Testen und Qualitätssicherung",
            "description": "Sicherstellung der Zuverlässigkeit und Leistung von Software durch rigorose Tests und Einhaltung von Qualitätsstandards."
          },
          "fr": {
            "title": "Tests et assurance qualité",
            "description": "Garantir la fiabilité et les performances des logiciels grâce à des tests rigoureux et au respect des normes de qualité."
          }
        }
      },

      {
        "imageIconUrl": null,
        "faIcon": "fas fa-bug-slash",
        "value": null,
        "locales": {
          "en": {
            "title": "Code Best Practices",
            "description": "My developer journey has always included the search for and implementation of code best practices."
          },
          "de": {
            "title": "Best Practices für Code",
            "description": "Meine Entwicklerreise beinhaltete immer die Suche und Implementierung von Best Practices für Code."
          },
          "fr": {
            "title": "Meilleures pratiques de code",
            "description": "Mon parcours de développeur a toujours inclus la recherche et la mise en œuvre des meilleures pratiques de code."
          }
        }
      },

      {
        "imageIconUrl": null,
        "faIcon": "fas fa-hard-drive",
        "value": null,
        "locales": {
          "en": {
            "title": "Hardware Integration",
            "description": "Seamlessly connecting software with hardware components to create integrated and functional systems."
          },
          "de": {
            "title": "Hardware-Integration",
            "description": "Nahtlose Verbindung von Software mit Hardwarekomponenten zur Schaffung integrierter und funktionaler Systeme."
          },
          "fr": {
            "title": "Intégration matérielle",
            "description": "Connexion transparente des logiciels aux composants matériels pour créer des systèmes intégrés et fonctionnels."
          }
        }
      },

      {
        "imageIconUrl": null,
        "faIcon": "fas fa-laptop-code",
        "value": null,
        "locales": {
          "en": {
            "title": "Prototyping",
            "description": "Bringing creativity to software development by exploring new ideas and concepts."
          },
          "de": {
            "title": "Prototyping",
            "description": "Kreativität in die Softwareentwicklung einbringen, indem neue Ideen und Konzepte erforscht werden."
          },
          "fr": {
            "title": "Prototypage",
            "description": "Apporter de la créativité au développement de logiciels en explorant de nouvelles idées et de nouveaux concepts."
          }
        }
      }
    ],

    "programming": [
      {
        "imageIconUrl": null,
        "faIcon": "fab fa-windows",
        "value": 95,
        "locales": {
          "en": {
            "title": "C#",
            "description": "Experience Time: 6 years"
          },
          "de": {
            "title": "C#",
            "description": "Erfahrungszeit: 6 Jahre"
          },
          "fr": {
            "title": "C#",
            "description": "Temps d'expérience : 6 ans"
          }
        }
      },
      {
        "imageIconUrl": null,
        "faIcon": "fab fa-windows",
        "value": 95,
        "locales": {
          "en": {
            "title": ".NET / .NET Framework",
            "description": "Experience Time: 6 years"
          },
          "de": {
            "title": ".NET / .NET Framework",
            "description": "Erfahrungszeit: 6 Jahre"
          },
          "fr": {
            "title": ".NET / .NET Framework",
            "description": "Temps d'expérience : 6 ans"
          }
        }
      },
      {
        "imageIconUrl": null,
        "faIcon": "fa fa-database",
        "value": 75,
        "locales": {
          "en": {
            "title": "SQL",
            "description": "Experience Time: 5 years"
          },
          "de": {
            "title": "SQL",
            "description": "Erfahrungszeit: 5 Jahre"
          },
          "fr": {
            "title": "SQL",
            "description": "Temps d'expérience : 5 ans"
          }
        }
      },
      {
        "imageIconUrl": null,
        "faIcon": "fab fa-docker",
        "value": 55,
        "locales": {
          "en": {
            "title": "Docker + Kubernetes",
            "description": "Experience Time: 2 years"
          },
          "de": {
            "title": "Docker + Kubernetes",
            "description": "Erfahrungszeit: 2 Jahre"
          },
          "fr": {
            "title": "Docker + Kubernetes",
            "description": "Temps d'expérience : 2 ans"
          }
        }
      },
      {
        "imageIconUrl": null,
        "faIcon": "fab fa-react",
        "value": 35,
        "locales": {
          "en": {
            "title": "React",
            "description": "Experience Time: 1 year"
          },
          "de": {
            "title": "React",
            "description": "Erfahrungszeit: 1 Jahr"
          },
          "fr": {
            "title": "React",
            "description": "Temps d'expérience : 1 an"
          }
        }
      },
      {
        "imageIconUrl": null,
        "faIcon": "fab fa-vuejs",
        "value": 15,
        "locales": {
          "en": {
            "title": "Vue",
            "description": "Experience Time: 2 months"
          },
          "de": {
            "title": "Vue",
            "description": "Erfahrungszeit: 2 Monate"
          },
          "fr": {
            "title": "Vue",
            "description": "Temps d'expérience : 2 mois"
          }
        }
      }
    ],

    "languages": [
      {
        "imageIconUrl": "images/flags/pt.png",
        "faIcon": null,
        "value": 100,
        "locales": {
          "en": {
            "title": "Portuguese",
            "description": "Native speaker."
          },
          "de": {
            "title": "Portugiesisch",
            "description": "Muttersprachler."
          },
          "fr": {
            "title": "Portugais",
            "description": "Locuteur natif."
          }
        }
      },

      {
        "imageIconUrl": "images/flags/en.png",
        "faIcon": null,
        "value": 90,
        "locales": {
          "en": {
            "title": "English",
            "description": "Fluent in both spoken and written English. Advanced in professional communication."
          },
          "de": {
            "title": "Englisch",
            "description": "Fliessende Englischkenntnisse in Wort und Schrift. Fortgeschrittene in der professionellen Kommunikation."
          },
          "fr": {
            "title": "Anglais",
            "description": "Anglais courant à la fois parlé et écrit. Avancé en communication professionnelle."
          }
        }
      },

      {
        "imageIconUrl": "images/flags/de.png",
        "faIcon": null,
        "value": 10,
        "locales": {
          "en": {
            "title": "German",
            "description": "Basic understanding of German. Learning and improving."
          },
          "de": {
            "title": "Deutsch",
            "description": "Grundkenntnisse der deutschen Sprache. Lernen und verbessern."
          },
          "fr": {
            "title": "Allemande",
            "description": "Compréhension de base de l'allemand. Apprendre et s'améliorer."
          }
        }
      }
    ],

    "extra": [
      {
        "imageIconUrl": null,
        "faIcon": "fas fa-comments",
        "value": null,
        "locales": {
          "en": {
            "title": "Communication Skills",
            "description": "Effectively conveying information, actively listening to others, and fostering clear and open dialogue within a team or organization."
          },
          "de": {
            "title": "Kommunikationsfähigkeit",
            "description": "Informationen effektiv vermitteln, aktiv zuhören und einen klaren und offenen Dialog innerhalb eines Teams oder einer Organisation fördern."
          },
          "fr": {
            "title": "Compétences en communication",
            "description": "Transmettre efficacement des informations, écouter activement les autres et favoriser un dialogue clair et ouvert au sein d'une équipe ou d'une organisation."
          }
        }
      },
      {
        "imageIconUrl": null,
        "faIcon": "fas fa-people-group",
        "value": null,
        "locales": {
          "en": {
            "title": "Team Spirit",
            "description": "Collaborating effectively with colleagues, contributing positively to a group dynamic, and working together towards shared goals and objectives."
          },
          "de": {
            "title": "Teamgeist",
            "description": "Effektiv mit Kollegen zusammenarbeiten, positiv zur Gruppendynamik beitragen und gemeinsam auf gemeinsame Ziele und Vorgaben hinarbeiten."
          },
          "fr": {
            "title": "Esprit d'équipe",
            "description": "Collaborer efficacement avec ses collègues, contribuer positivement à la dynamique d'un groupe et travailler ensemble à la réalisation d'objectifs communs."
          }
        }
      },
      {
        "imageIconUrl": null,
        "faIcon": "fas fa-book",
        "value": null,
        "locales": {
          "en": {
            "title": "Eager to Learn",
            "description": "Demonstrating a proactive approach to acquiring new knowledge, embracing opportunities for professional development, and continuously seeking to improve skills and expertise."
          },
          "de": {
            "title": "Lernbereitschaft",
            "description": "Eine proaktive Haltung zum Erwerb neuen Wissens zeigen, Möglichkeiten zur beruflichen Weiterentwicklung nutzen und kontinuierlich versuchen, Fähigkeiten und Fachwissen zu verbessern."
          },
          "fr": {
            "title": "Désir d'apprendre",
            "description": "Démontrer une approche proactive de l'acquisition de nouvelles connaissances, saisir les opportunités de développement professionnel et chercher continuellement à améliorer ses compétences et son expertise."
          }
        }
      },
      {
        "imageIconUrl": null,
        "faIcon": "fas fa-wrench",
        "value": null,
        "locales": {
          "en": {
            "title": "Adaptability",
            "description": "Able to adjust to changing circumstances, new technologies, and evolving work environments."
          },
          "de": {
            "title": "Anpassungsfähigkeit",
            "description": "Sich an veränderte Umstände, neue Technologien und sich entwickelnde Arbeitsumgebungen anpassen können."
          },
          "fr": {
            "title": "Adaptabilité",
            "description": "Être capable de s'adapter aux circonstances changeantes, aux nouvelles technologies et à l'évolution des environnements de travail."
          }
        }
      },
      {
        "imageIconUrl": null,
        "faIcon": "fas fa-triangle-exclamation",
        "value": null,
        "locales": {
          "en": {
            "title": "Problem-solving",
            "description": "Identifying and analyzing challenges, developing creative solutions, and implementing effective strategies to overcome obstacles and achieve desired outcomes."
          },
          "de": {
            "title": "Problemlösungsfähigkeit",
            "description": "Herausforderungen identifizieren und analysieren, kreative Lösungen entwickeln und effektive Strategien implementieren, um Hindernisse zu überwinden und die gewünschten Ergebnisse zu erzielen."
          },
          "fr": {
            "title": "Résolution de problèmes",
            "description": "Identifier et analyser les défis, développer des solutions créatives et mettre en œuvre des stratégies efficaces pour surmonter les obstacles et atteindre les résultats souhaités."
          }
        }
      },
      {
        "imageIconUrl": null,
        "faIcon": "fas fa-stopwatch",
        "value": null,
        "locales": {
          "en": {
            "title": "Time management",
            "description": "Organizing and prioritizing tasks efficiently, setting realistic deadlines, and utilizing resources effectively to maximize productivity and achieve timely completion of work."
          },
          "de": {
            "title": "Zeitmanagement",
            "description": "Aufgaben effizient organisieren und priorisieren, realistische Fristen setzen und Ressourcen effektiv nutzen, um die Produktivität zu maximieren und die rechtzeitige Erledigung der Arbeit zu gewährleisten."
          },
          "fr": {
            "title": "Gestion du temps",
            "description": "Organiser etPrioriser efficacement les tâches, fixer des délais réalistes et utiliser efficacement les ressources pour maximiser la productivité et assurer la réalisation du travail dans les délais."
          }
        }
      }
    ]
  }
}
